emcpy.py
exceptions.py
methods.py
util.py
emcpy-0.2.2.dist-info/LICENSE.txt
emcpy-0.2.2.dist-info/METADATA
emcpy-0.2.2.dist-info/WHEEL
emcpy-0.2.2.dist-info/top_level.txt
emcpy-0.2.2.dist-info/RECORD
